[
    {
        "contrato_id": "634252",
        "uasg_code": "787010",
        "status": "PORTARIA",
        "objeto_editado": "VIATURA SUV COM BLINDAGEM NÍVEL III",
        "portaria_edit": "teste da portaria",
        "termo_aditivo_edit": "teste do termo aditivo",
        "radio_options_json": "{\"Pode Renovar?\": \"Sim\", \"Custeio?\": \"Sim\", \"Natureza Continuada?\": \"N\\u00e3o\", \"Material/Servi\\u00e7o:\": \"Material\"}",
        "data_registro": "29/10/2025 11:34:27",
        "registros": [
            "29/10/2025 - teste para analise de registro - PORTARIA"
        ],
        "registros_mensagem": [],
        "link_contrato": "https://github.com/Paulo-JDev/projeto_pric-OBT.git",
        "link_ta": "https://www.youtube.com/watch?v=x7fGTGMYYOY&list=RDMM&index=5",
        "link_portaria": "https://www.youtube.com/watch?v=vvG3LjSrNN0",
        "link_pncp_espc": "https://github.com/Paulo-JDev/projeto_pric-OBT.git",
        "link_portal_marinha": "https://www.youtube.com/watch?v=x7fGTGMYYOY&list=RDMM&index=5",
        "fiscal_gestor": "teste gestor do contrato",
        "fiscal_titular": "teste do titular",
        "fiscal_substituto": "teste do fiscal substituto",
        "fiscal_setor_responsavel": "teste do setor responsavel",
        "fiscal_data": "teste da data de fiscalização",
        "fiscal_observacoes": "alguma obsdrvação se necessaria",
        "fiscal_acoes_corretivas": "teste acoes corretivas para analise",
        "fiscal_data_criacao": "29/10/2025 11:03:22",
        "fiscal_data_atualizacao": "29/10/2025 11:34:27"
    }
]