{
    "id_contrato": 458702,
    "uasg": "787010",
    "status": "Ata Gerada",
    "comments": [],
    "objeto": "CONTRATAÇÃO DE EMPRESA ESPECIALIZADA NA PRESTAÇÃO DE SERVIÇO DE TRANSPORTE, PORTA A PORTA, EM CAMINHÃO FECHADO, TIPO BAÚ, DE MOBILIÁRIO, EQUIPAMENTOS, BENS PESSOAIS, AUTOMÓVEIS E MOTOCICLETAS EM TERRITÓRIO NACIONAL POR MEIO RODOVIÁRIO, CONSTANDO TODAS AS DESPESAS INCLUSIVE SEGURO ESPECÍFICO POR SERVIÇO DE TRANSPORTE, PARA ATENDER ÀS NECESSIDADES DOS MILITARES E SEUS DEPENDENTES, E SERVIDORES CIVIS NA ÁREA DE COMPETÊNCIA DO COMANDO DO 7º DISTRITO NAVAL(COM7ºDN), MOVIMENTADOS PARA OUTRAS LOCALIDADES DO TERRITÓRIO NACIONAL; ASSIM COMO DOS MILITARES LICENCIADOS, POR CONCLUSÃO DO TEMPO DE SERVIÇO OU DE EX OFFICIO ESTÁGIO E POR CONVENIÊNCIA DO SERVIÇO, NAS CONDIÇÕES ESTABELECIDAS NO TERMO DE REFERÊNCIA.",
    "radio_options": {
        "Pode Renovar?": "Sim",
        "Custeio?": "Sim",
        "Natureza Continuada?": "Sim",
        "Material/Serviço:": "Material"
    }
}